Metadata-Version: 2.1
Name: deepfos-ipc-protocol
Version: 1.2.1
Summary: deepfos系统使用的unix socket协议
Author: chenxingyu
Author-email: chenxingyu1021@mail.com
Classifier: Development Status :: 3 - Alpha
Classifier: Intended Audience :: Developers
Classifier: Topic :: Software Development :: Libraries :: Python Modules
Classifier: Programming Language :: Python :: 3.8
Classifier: Programming Language :: Python :: 3.9
Classifier: Programming Language :: Python :: 3.10
Classifier: Operating System :: OS Independent
Requires-Python: >=3.8.3
Requires-Dist: loguru (~=0.5.3)
